elorus/__init__.py
elorus/auth.py
elorus/client.py
elorus/exceptions.py
elorus/models.py
elorus/typings.py
elorus-0.1.1.dist-info/LICENSE
elorus-0.1.1.dist-info/METADATA
elorus-0.1.1.dist-info/WHEEL
elorus-0.1.1.dist-info/RECORD
