Metadata-Version: 2.1
Name: elorus
Version: 0.1.1
Summary: 
Author: Oluwafemi Adenuga
Author-email: femi@withlogic.co
Requires-Python: >=3.12,<4.0
Classifier: Programming Language :: Python :: 3
Classifier: Programming Language :: Python :: 3.12
Requires-Dist: httpx (>=0.27.0,<0.28.0)
